binit/__init__.py
binit/align.py
binit/bin.py
binit-0.0.3.dist-info/METADATA
binit-0.0.3.dist-info/WHEEL
binit-0.0.3.dist-info/top_level.txt
binit-0.0.3.dist-info/RECORD
