Metadata-Version: 2.1
Name: binit
Version: 0.0.3
Summary: Timestamp binning package
Home-page: https://github.com/Ruairi-osul/binit
Author: Ruairi O'Sullivan
Author-email: ruairi.osullivan.work@gmail.com
License: GNU GPLv3
Project-URL: Source, https://github.com/Ruairi-osul/binit
Keywords: data-analysis data-science array timestamps alignment
Requires-Python: >=3.6
Requires-Dist: numpy
